odoo/addons/base_fontawesome_web_editor/README.rst
odoo/addons/base_fontawesome_web_editor/__init__.py
odoo/addons/base_fontawesome_web_editor/__manifest__.py
odoo/addons/base_fontawesome_web_editor/i18n/base_fontawesome_web_editor.pot
odoo/addons/base_fontawesome_web_editor/readme/CONTRIBUTORS.md
odoo/addons/base_fontawesome_web_editor/readme/DESCRIPTION.md
odoo/addons/base_fontawesome_web_editor/readme/USAGE.md
odoo/addons/base_fontawesome_web_editor/static/description/icon.png
odoo/addons/base_fontawesome_web_editor/static/description/index.html
odoo/addons/base_fontawesome_web_editor/static/src/js/wysiwyg/fonts.esm.js
odoo_addon_base_fontawesome_web_editor-17.0.1.0.1.dist-info/METADATA
odoo_addon_base_fontawesome_web_editor-17.0.1.0.1.dist-info/WHEEL
odoo_addon_base_fontawesome_web_editor-17.0.1.0.1.dist-info/top_level.txt
odoo_addon_base_fontawesome_web_editor-17.0.1.0.1.dist-info/RECORD
