Metadata-Version: 2.1
Name: odoo-addon-base_fontawesome_web_editor
Version: 17.0.1.0.1
Requires-Python: >=3.10
Requires-Dist: odoo-addon-base_fontawesome>=17.0dev,<17.1dev
Requires-Dist: odoo>=17.0a,<17.1dev
Summary: Integration between base_fontawesome and web_editor for FontAwesome >= 6.7.2 support.
Home-page: https://github.com/OCA/server-tools
License: LGPL-3
Author: =?utf-8?q?Heligr=C3=A0fics_Fotogrametr=C3=ADa_S=2EL=2E=2C_Odoo_Community_Association_=28OCA=29?=
Author-email: support@odoo-community.org
Classifier: Programming Language :: Python
Classifier: Framework :: Odoo
Classifier: Framework :: Odoo :: 17.0
Classifier: License :: OSI Approved :: GNU Lesser General Public License v3 (LGPLv3)
